teams_puppet/__init__.py
teams_puppet-0.2.0.dist-info/LICENSE
teams_puppet-0.2.0.dist-info/METADATA
teams_puppet-0.2.0.dist-info/WHEEL
teams_puppet-0.2.0.dist-info/RECORD
