Metadata-Version: 2.1
Name: teams-puppet
Version: 0.2.0
Summary: Retrieves teams users JSON web tokens.
Home-page: https://github.com/Jheesbrough/MS-Teams-Puppet-Account-Manager
Author: Jheesbrough
Author-email: 71599416+Jheesbrough@users.noreply.github.com
Requires-Python: >=3.10,<4.0
Classifier: Programming Language :: Python :: 3
Classifier: Programming Language :: Python :: 3.10
Classifier: Programming Language :: Python :: 3.11
Classifier: Programming Language :: Python :: 3.12
Requires-Dist: apscheduler (>=3.10.4,<4.0.0)
Requires-Dist: blinker (<1.8.0)
Requires-Dist: selenium (>=4.23.1,<5.0.0)
Requires-Dist: setuptools (>=71.0.3,<72.0.0)
Requires-Dist: webdriver-manager (>=4.0.1,<5.0.0)
Project-URL: Repository, https://github.com/Jheesbrough/MS-Teams-Puppet-Account-Manager
